hotspot3/__init__.py
hotspot3/__main__.py
hotspot3/cli.py
hotspot3/config.py
hotspot3/extract_pvals.py
hotspot3/from_configs.py
hotspot3/multiple_sample_fdr.py
hotspot3/processors.py
hotspot3/track_memory.py
hotspot3/background_fit/__init__.py
hotspot3/background_fit/defunc.py
hotspot3/background_fit/fit.py
hotspot3/background_fit/genomic_background_fit.py
hotspot3/background_fit/regression.py
hotspot3/connectors/__init__.py
hotspot3/connectors/babachi.py
hotspot3/connectors/bam2bed.py
hotspot3/connectors/bottleneck.py
hotspot3/helpers/__init__.py
hotspot3/helpers/colors.py
hotspot3/helpers/format_converters.py
hotspot3/helpers/models.py
hotspot3/helpers/stats.py
hotspot3/helpers/utils.py
hotspot3/io/__init__.py
hotspot3/io/logging.py
hotspot3/io/paths.py
hotspot3/io/readers.py
hotspot3/io/writers.py
hotspot3/peak_calling/__init__.py
hotspot3/peak_calling/peak_calling.py
hotspot3/scoring/__init__.py
hotspot3/scoring/fdr.py
hotspot3/scoring/pvalue.py
hotspot3/scripts/__init__.py
hotspot3/scripts/extract_cutcounts.sh
hotspot3/signal_smoothing/__init__.py
hotspot3/signal_smoothing/modwt.py
hotspot3-1.0.1.dist-info/licenses/LICENSE
hotspot3-1.0.1.dist-info/METADATA
hotspot3-1.0.1.dist-info/WHEEL
hotspot3-1.0.1.dist-info/entry_points.txt
hotspot3-1.0.1.dist-info/top_level.txt
hotspot3-1.0.1.dist-info/RECORD
