Metadata-Version: 2.4
Name: hotspot3
Version: 1.0.1
Summary: Chromatin accessibility peak caller with an adaptive background model
Author: Sergey Abramov, Alexandr Boytsov, Jeff Vierstra
License:                     GNU GENERAL PUBLIC LICENSE
Project-URL: Homepage, https://github.com/vierstralab/hotspot3
Requires-Python: >=3.7
License-File: LICENSE
Requires-Dist: numpy==1.26.0
Requires-Dist: pandas
Requires-Dist: scipy
Requires-Dist: statsmodels
Requires-Dist: pysam
Requires-Dist: tqdm
Requires-Dist: PyWavelets
Requires-Dist: scikit-learn
Requires-Dist: pyarrow
Requires-Dist: Bottleneck
Requires-Dist: pyBigWig
Requires-Dist: networkx
Requires-Dist: babachi==3.0.0
Requires-Dist: genome-tools==2.0.0
Dynamic: license-file
